cloudsync_gdrive.py
cloudsync_gdrive-2.0.1.dist-info/entry_points.txt
cloudsync_gdrive-2.0.1.dist-info/LICENSE
cloudsync_gdrive-2.0.1.dist-info/WHEEL
cloudsync_gdrive-2.0.1.dist-info/METADATA
cloudsync_gdrive-2.0.1.dist-info/RECORD
